bytesioex/__init__.py
bytesioex/py.typed
bytesioex-0.1.2.dist-info/LICENSE
bytesioex-0.1.2.dist-info/METADATA
bytesioex-0.1.2.dist-info/WHEEL
bytesioex-0.1.2.dist-info/top_level.txt
bytesioex-0.1.2.dist-info/RECORD
