Metadata-Version: 2.1
Name: bytesioex
Version: 0.1.2
Summary: A simple wrapper over io.BytesIO which allows reading and writing C data types
Home-page: https://github.com/demberto/BytesIOEx
Author: demberto
Author-email: demberto@protonmail.com
License: MIT
Project-URL: Bug Tracker, https://github.com/demberto/BytesIOEx/issues
Classifier: Development Status :: 4 - Beta
Classifier: Intended Audience :: Developers
Classifier: License :: OSI Approved :: MIT License
Classifier: Natural Language :: English
Classifier: Operating System :: OS Independent
Classifier: Programming Language :: Python :: 3
Classifier: Programming Language :: Python :: 3 :: Only
Classifier: Programming Language :: Python :: 3.6
Classifier: Programming Language :: Python :: 3.7
Classifier: Programming Language :: Python :: 3.8
Classifier: Programming Language :: Python :: 3.9
Classifier: Programming Language :: Python :: 3.10
Classifier: Topic :: Software Development :: Libraries :: Python Modules
Classifier: Typing :: Typed
Requires-Python: >=3.6
License-File: LICENSE
